odoo/addons/sale_timesheet_hook/README.rst
odoo/addons/sale_timesheet_hook/__init__.py
odoo/addons/sale_timesheet_hook/__manifest__.py
odoo/addons/sale_timesheet_hook/i18n/de.po
odoo/addons/sale_timesheet_hook/i18n/es.po
odoo/addons/sale_timesheet_hook/i18n/it.po
odoo/addons/sale_timesheet_hook/i18n/sale_timesheet_hook.pot
odoo/addons/sale_timesheet_hook/models/__init__.py
odoo/addons/sale_timesheet_hook/models/account_analytic_line.py
odoo/addons/sale_timesheet_hook/readme/CONTRIBUTORS.rst
odoo/addons/sale_timesheet_hook/readme/DESCRIPTION.rst
odoo/addons/sale_timesheet_hook/static/description/icon.png
odoo/addons/sale_timesheet_hook/static/description/index.html
odoo/addons/sale_timesheet_hook/tests/__init__.py
odoo/addons/sale_timesheet_hook/wizard/__init__.py
odoo/addons/sale_timesheet_hook/wizard/project_create_sale_order.py
odoo12_addon_sale_timesheet_hook-12.0.1.0.0.99.dev14.dist-info/METADATA
odoo12_addon_sale_timesheet_hook-12.0.1.0.0.99.dev14.dist-info/WHEEL
odoo12_addon_sale_timesheet_hook-12.0.1.0.0.99.dev14.dist-info/top_level.txt
odoo12_addon_sale_timesheet_hook-12.0.1.0.0.99.dev14.dist-info/RECORD
